so3/__init__.py
so3/bindings.cpython-38-darwin.so
so3-1.3.6.dist-info/LICENSE
so3-1.3.6.dist-info/METADATA
so3-1.3.6.dist-info/WHEEL
so3-1.3.6.dist-info/top_level.txt
so3-1.3.6.dist-info/RECORD
